{
  "_id": "Q-220-1201-2.0-2.6-003",
  "cert_id": [
    "220-1201"
  ],
  "domain_id": "2.0",
  "domain_title": "Networking",
  "subdomain_id": "2.6",
  "difficulty": "easy",
  "question_type": "multiple_choice",
  "question_text": "What is each of the four numbers in an IPv4 address called?",
  "answer_options": [
    "Nibble",
    "Hex block",
    "Octet",
    "Byte pair"
  ],
  "correct_answer": [
    "Octet"
  ],
  "explanation": "Each section of an IPv4 address is called an octet because it represents 8 bits.",
  "tags": [
    "IPv4",
    "octet"
  ],
  "status": "approved",
  "image": null,
  "media": null,
  "requiredCount": null,
  "__v": 0
}