{
  "_id": "Q-220-1201-2.0-2.6-005",
  "cert_id": [
    "220-1201"
  ],
  "domain_id": "2.0",
  "domain_title": "Networking",
  "subdomain_id": "2.6",
  "difficulty": "easy",
  "question_type": "multiple_choice",
  "question_text": "Why are private IPv4 addresses used in a network?",
  "answer_options": [
    "They are encrypted for security",
    "They are only used for IPv6 routing",
    "They allow multiple internal devices to share a single public IP via NAT",
    "They enable faster connections across the internet"
  ],
  "correct_answer": [
    "They allow multiple internal devices to share a single public IP via NAT"
  ],
  "explanation": "Private IPs are used inside a network and mapped to a single public IP using Network Address Translation (NAT).",
  "tags": [
    "IPv4",
    "public IP",
    "IP address"
  ],
  "status": "approved",
  "image": null,
  "media": null,
  "requiredCount": null,
  "__v": 0
}