{
  "_id": "Q-220-1201-1.0-1.1-015",
  "cert_id": [
    "220-1201"
  ],
  "domain_id": "1.0",
  "domain_title": "Mobile Devices",
  "subdomain_id": "1.1",
  "difficulty": "medium",
  "question_type": "select_multiple",
  "question_text": "Select two advantages of lithium-ion (Li-ion) laptop batteries.",
  "answer_options": [
    "They are very inexpensive",
    "They do not suffer from memory effect",
    "They are lightweight",
    "They are easily recycled",
    "They are commonly used in CRT monitors"
  ],
  "correct_answer": [
    "They do not suffer from memory effect",
    "They are lightweight"
  ],
  "tags": [
    "lithium ion",
    "no memory effect"
  ],
  "status": "approved",
  "image": null,
  "media": null,
  "requiredCount": null,
  "__v": 0
}