{
  "_id": "Q-220-1201-1.0-1.3-039",
  "cert_id": [
    "220-1201"
  ],
  "domain_id": "1.0",
  "domain_title": "Mobile Devices",
  "subdomain_id": "1.3",
  "difficulty": "easy",
  "question_type": "select_all",
  "question_text": "Which of the following are examples of Bluetooth-enabled devices that can be paired with a smartphone? (Select all that apply)",
  "answer_options": [
    "Wireless headphones",
    "Fitness trackers",
    "Bluetooth speakers",
    "Wired Ethernet routers"
  ],
  "correct_answer": [
    "Wireless headphones",
    "Fitness trackers",
    "Bluetooth speakers"
  ],
  "explanation": "Bluetooth is commonly used with wireless audio devices and wearables. Wired routers do not use Bluetooth.",
  "tags": [
    "Bluetooth",
    "wireless speaker",
    "fitness tracker",
    "pairing"
  ],
  "status": "approved",
  "image": null,
  "media": null,
  "requiredCount": null,
  "__v": 0
}