{
  "_id": "Q-220-1201-2.0-2.4-043",
  "cert_id": [
    "220-1201"
  ],
  "domain_id": "2.0",
  "domain_title": "Networking",
  "subdomain_id": "2.4",
  "difficulty": "hard",
  "question_type": "select_all",
  "question_text": "Which of the following statements about DNS subdomains are correct? (Select all that apply)",
  "answer_options": [
    "Subdomains inherit the structure from their parent domains",
    "Subdomains must always resolve to a different IP than the parent domain",
    "Subdomains increase flexibility in DNS and service organization",
    "Subdomains are resolved independently of the FQDN structure",
    "Subdomains can be nested multiple levels deep"
  ],
  "correct_answer": [
    "Subdomains inherit the structure from their parent domains",
    "Subdomains increase flexibility in DNS and service organization",
    "Subdomains can be nested multiple levels deep"
  ],
  "explanation": "Subdomains expand DNS structure by enabling hierarchical service names, often nested deeply for internal use or load segmentation.",
  "tags": [
    "subdomain",
    "hierarchy"
  ],
  "status": "approved",
  "image": null,
  "media": null,
  "requiredCount": null,
  "__v": 0
}