{
  "_id": "Q-220-1201-2.0-2.7-016",
  "cert_id": [
    "220-1201"
  ],
  "domain_id": "2.0",
  "domain_title": "Networking",
  "subdomain_id": "2.7",
  "difficulty": "easy",
  "question_type": "multiple_choice",
  "question_text": "Which of the following is a common use for fiber optics in a metropolitan area?",
  "answer_options": [
    "Infrared remotes",
    "Home cable service",
    "SONET ring for WAN connections",
    "Bluetooth access points"
  ],
  "correct_answer": [
    "SONET ring for WAN connections"
  ],
  "explanation": "SONET rings are often used with fiber in metro and WAN connections to ensure high bandwidth and fault tolerance.",
  "tags": [
    "SONET",
    "metro Ethernet"
  ],
  "status": "approved",
  "image": null,
  "media": null,
  "requiredCount": null,
  "__v": 0
}