{
  "_id": "Q-220-1201-2.0-2.8-001",
  "cert_id": [
    "220-1201"
  ],
  "domain_id": "2.0",
  "domain_title": "Networking",
  "subdomain_id": "2.8",
  "difficulty": "easy",
  "question_type": "multiple_choice",
  "question_text": "What tool is primarily used to attach an RJ45 connector to a twisted pair cable?",
  "answer_options": [
    "Tone generator",
    "Cable tester",
    "Crimper",
    "Loopback plug"
  ],
  "correct_answer": [
    "Crimper"
  ],
  "explanation": "A crimper is a specialized tool used to press an RJ45 connector onto a twisted pair cable, securing both the electrical and mechanical connection.",
  "tags": [
    "crimper"
  ],
  "status": "approved",
  "image": null,
  "media": null,
  "requiredCount": null,
  "__v": 0
}