{
  "_id": "Q-220-1201-2.0-2.1-046",
  "cert_id": [
    "220-1201"
  ],
  "domain_id": "2.0",
  "domain_title": "Networking",
  "subdomain_id": "2.1",
  "difficulty": "medium",
  "question_type": "multiple_choice",
  "question_text": "Which protocol uses TCP port 143 to allow email synchronization across multiple devices?",
  "answer_options": [
    "POP3",
    "SMTP",
    "IMAP",
    "FTP"
  ],
  "correct_answer": [
    "IMAP"
  ],
  "explanation": "IMAP (Internet Message Access Protocol) runs on TCP port 143 and keeps email messages on the server for access across devices.",
  "tags": [
    "IMAP",
    "email",
    "port assignment"
  ],
  "status": "approved",
  "image": null,
  "media": null,
  "requiredCount": null,
  "__v": 0
}