{
  "_id": "Q-220-1201-2.0-2.1-032",
  "cert_id": [
    "220-1201"
  ],
  "domain_id": "2.0",
  "domain_title": "Networking",
  "subdomain_id": "2.1",
  "difficulty": "easy",
  "question_type": "multiple_choice",
  "question_text": "Which of the following is a common use case for UDP?",
  "answer_options": [
    "File transfer with confirmation",
    "Secure shell remote login",
    "Real-time voice communication",
    "Encrypted web browsing"
  ],
  "correct_answer": [
    "Real-time voice communication"
  ],
  "explanation": "UDP is preferred for real-time traffic such as voice or video communication due to its low latency.",
  "tags": [
    "real-time traffic",
    "UDP",
    "streaming"
  ],
  "status": "approved",
  "image": null,
  "media": null,
  "requiredCount": null,
  "__v": 0
}